lloca/__init__.py
lloca/backbone/__init__.py
lloca/backbone/attention.py
lloca/backbone/graphnet.py
lloca/backbone/lloca_message_passing.py
lloca/backbone/mlp.py
lloca/backbone/particlenet.py
lloca/backbone/particletransformer.py
lloca/backbone/transformer.py
lloca/backbone/transformer_v2.py
lloca/backbone/attention_backends/__init__.py
lloca/backbone/attention_backends/flash.py
lloca/backbone/attention_backends/flex.py
lloca/backbone/attention_backends/mask.py
lloca/backbone/attention_backends/native.py
lloca/backbone/attention_backends/varlen.py
lloca/backbone/attention_backends/xformers.py
lloca/equivectors/__init__.py
lloca/equivectors/base.py
lloca/equivectors/lgatr.py
lloca/equivectors/mlp.py
lloca/equivectors/pelican.py
lloca/framesnet/__init__.py
lloca/framesnet/equi_frames.py
lloca/framesnet/frames.py
lloca/framesnet/nonequi_frames.py
lloca/reps/__init__.py
lloca/reps/tensorreps.py
lloca/reps/tensorreps_transform.py
lloca/utils/__init__.py
lloca/utils/lorentz.py
lloca/utils/orthogonalize_3d.py
lloca/utils/orthogonalize_4d.py
lloca/utils/polar_decomposition.py
lloca/utils/rand_transforms.py
lloca/utils/utils.py
lloca-1.3.5.dist-info/licenses/LICENSE
lloca-1.3.5.dist-info/METADATA
lloca-1.3.5.dist-info/WHEEL
lloca-1.3.5.dist-info/entry_points.txt
lloca-1.3.5.dist-info/top_level.txt
lloca-1.3.5.dist-info/RECORD
