Metadata-Version: 2.4
Name: lloca
Version: 1.3.5
Summary: Lorentz Local Canonicalization
Author-email: Jonas Spinner <j.spinner@thphys.uni-heidelberg.de>, Luigi Favaro <luigi.favaro@uclouvain.be>
Project-URL: homepage, https://github.com/heidelberg-hepml/lloca
Project-URL: repository, https://github.com/heidelberg-hepml/lloca
Requires-Python: >=3.10
License-File: LICENSE
Requires-Dist: torch>=2.1
Requires-Dist: torch-geometric>=2.3.0
Requires-Dist: lgatr
Requires-Dist: pelican-lite
Provides-Extra: varlen-attention
Requires-Dist: torch>=2.10; extra == "varlen-attention"
Provides-Extra: xformers-attention
Requires-Dist: xformers; extra == "xformers-attention"
Provides-Extra: flex-attention
Requires-Dist: torch>=2.7; extra == "flex-attention"
Provides-Extra: flash-attention
Requires-Dist: flash-attn; extra == "flash-attention"
Provides-Extra: dev
Requires-Dist: pre-commit; extra == "dev"
Requires-Dist: pytest; extra == "dev"
Requires-Dist: pytest-cov; extra == "dev"
Requires-Dist: sphinx<9.0; extra == "dev"
Requires-Dist: sphinx-autodoc-typehints; extra == "dev"
Requires-Dist: sphinx-rtd-theme; extra == "dev"
Dynamic: license-file
